viewdom/__init__.py
viewdom/py.typed
viewdom/version.py
viewdom-0.6.5.dist-info/METADATA
viewdom-0.6.5.dist-info/WHEEL
viewdom-0.6.5.dist-info/licenses/LICENSE.md
viewdom-0.6.5.dist-info/RECORD
