Metadata-Version: 2.1
Name: viewdom
Version: 0.6.5
Summary: ViewDOM
Author-email: Paul Everitt <pauleveritt@me.com>
License-Expression: MIT
License-File: LICENSE.md
Classifier: Development Status :: 3 - Alpha
Classifier: Programming Language :: Python :: 3.11
Classifier: Programming Language :: Python :: 3.12
Requires-Python: >=3.11
Requires-Dist: hopscotch>=0.3.1
Requires-Dist: htm~=0.1.1
Requires-Dist: markupsafe~=2.1.3
Requires-Dist: tagged~=0.0.2
Requires-Dist: venusian~=3.1.0
